#######################################################################################################################################
<poster>MafiaTVRepo</poster>
<fanart></fanart>
#######################################################################################################################################

##############################################################################################################################

<item>
<title>The Bourne Identity (2002) 720p</title>
<link>http://movreel.com/cr838wkm1ink</link>
<thumbnail>https://encrypted-tbn1.gstatic.com/images?q=tbn:ANd9GcR5vDCDjapXWeClScODBtW3pX1AQtR3GWTZWJ1ljhRAx8WfM3hz</thumbnail>
</item>

<item>
<title>The Bourne Ultimatum (2007) 720p</title>
<link>http://movreel.com/u1lydlsm8i95</link>
<thumbnail>http://www.impawards.com/2007/posters/bourne_ultimatum_ver4.jpg</thumbnail>
</item>

<item>
<title>The Bourne Supremacy (2004) 720p</title>
<link>http://movreel.com/j15fj6l014wm</link>
<thumbnail>https://encrypted-tbn1.gstatic.com/images?q=tbn:ANd9GcRxZ28we_YP8uZF3RbMDix6Cstzpgr_SdUxBdiEin5gxgl1J0GHGw</thumbnail>
</item>

<item>
<title>Taken (2008) 720p</title>
<link>http://movreel.com/1sp8y91659x3</link>
<thumbnail>https://encrypted-tbn0.gstatic.com/images?q=tbn:ANd9GcRXKEtamrVD_OvMhR_WNaDnbQ8rgsx2CayVlGji1l1CZyh4wRTH_w</thumbnail>
</item>

<item>
<title>The Hunt for Red October (1990) 720p</title>
<link>http://movreel.com/r4y471zcbb98#</link>
<thumbnail>https://encrypted-tbn2.gstatic.com/images?q=tbn:ANd9GcQ4byYB_1eM5-sL8DPkPYc8fmFHvaI_crVj_RfNuGSQ4SqJWkbaRQ</thumbnail>
</item>

<item>
<title>Spy Game (2001) 720p</title>
<link>http://movreel.com/h2i8k1c5h6z2</link>
<thumbnail>https://www.movieposter.com/posters/archive/main/97/MPW-48801</thumbnail>
</item>

<item>
<title>Clear and Present Danger (1994) 1080p</title>
<link>http://mightyupload.com/k3zhxypeo1ru</link>
<thumbnail>https://encrypted-tbn0.gstatic.com/images?q=tbn:ANd9GcTSWqW1UU-ZpH5ggXuMfS8tiaUB8iCUQu4Fkp_QFL0ifQYCS2dQpA</thumbnail>
</item>

<item>
<title>Casino Royale (2006) 720p</title>
<link>http://movreel.com/d7iogc4zud0a</link>
<thumbnail>http://www.impawards.com/2006/posters/casino_royale_ver3.jpg</thumbnail>
</item>

<item>
<title>Mission: Impossible (1996)</title>
<link>http://vidto.me/5ouzfqeuyhe9</link>
<thumbnail>http://www.impawards.com/1996/posters/mission_impossible.jpg</thumbnail>
</item>

<item>
<title>Three Days of the Condor (1975) 720p</title>
<link>http://played.to/7gop7es1mb2d</link>
<thumbnail>http://themoviebros.files.wordpress.com/2010/08/three-days-of-the-condor-cover-3.jpg</thumbnail>
</item>

<item>
<title>Enemy of the State (1998) 720p</title>
<link>http://movreel.com/fcdj4pk3nu7c</link>
<thumbnail>http://www.impawards.com/1998/posters/enemy_of_the_state.jpg</thumbnail>
</item>

<item>
<title>The Good Shepherd (2006) 720p</title>
<link>http://movreel.com/e7hhtj0ocgl0</link>
<thumbnail>http://static.dramastyle.com/images/3/8/7625/The-Good-Shepherd_7625_5.jpg</thumbnail>
</item>

<item>
<title>Ronin (1998)</title>
<link>http://stagevu.com/video/prugaulpvjgb</link>
<thumbnail>https://encrypted-tbn2.gstatic.com/images?q=tbn:ANd9GcSKjJJKTB3nPqrUGGDrdPii1ghwzXO6Bd4LTYoLiVDN7AHaxlTz</thumbnail>
</item>

<item>
<title>The Recruit (2003)</title>
<link>http://stagevu.com/video/tekewxpdgeqa</link>
<thumbnail>https://encrypted-tbn1.gstatic.com/images?q=tbn:ANd9GcTdCP-qiqaixgQBHoq0qPocggrreuhOeD2bCgmu4dQ8hbGzO5JR</thumbnail>
</item>

<item>
<title>Syriana (2005)</title>
<link>http://stagevu.com/video/qyrwbppuimph</link>
<thumbnail>http://movieposters.2038.net/p/Syriana.jpg</thumbnail>
</item>

<item>
<title>Mission: Impossible III (2006)</title>
<link>http://vidto.me/95tnt4e055c</link>
<thumbnail>https://encrypted-tbn3.gstatic.com/images?q=tbn:ANd9GcTIhYo8SUMN5oeQnpoIOYDqYcFsiEFGqmUawJb1tc5nfS4KhbJw</thumbnail>
</item>

<item>
<title>JFK (1991) 720p</title>
<link>http://movreel.com/sl2mc5bh8ys4#</link>
<thumbnail>https://encrypted-tbn1.gstatic.com/images?q=tbn:ANd9GcTnb3rRT7tH3dnwHEAPgKiNeTO66XiyHXCIPeZeM-kV7MOEkndk</thumbnail>
</item>

<item>
<title>Mission: Impossible - Ghost Protocol (2011) 720p</title>
<link>http://vodlocker.com/opo70bnw0uec</link>
<thumbnail>http://ia.media-imdb.com/images/M/MV5BMTY4MTUxMjQ5OV5BMl5BanBnXkFtZTcwNTUyMzg5Ng@@._V1_SX640_SY720_.jpg</thumbnail>
</item>

<item>
<title>Body of Lies (2008)</title>
<link>http://movreel.com/ibyj0a9uknfu#</link>
<thumbnail>https://encrypted-tbn3.gstatic.com/images?q=tbn:ANd9GcRADEdJ6019wB06bolXhGD5Z4Gw5bpIk5gywu9kTW5iWgunuP3r</thumbnail>
</item>

<item>
<title>Argo (2012) 720p</title>
<link>http://movreel.com/6603p2m61bw6</link>
<thumbnail>http://www.beyondhollywood.com/uploads/2012/04/Argo-2012-Movie-Poster-600x887.jpg</thumbnail>
</item>

<item>
<title>Charlie Wilson's War (2007)</title>
<link>http://vodlocker.com/1nvyxodfdknd</link>
<thumbnail>https://encrypted-tbn1.gstatic.com/images?q=tbn:ANd9GcQ9PY73vMPXapf_dqEyKMpCNMsm3M7P_MRxoJiEkACaYnTxuYax</thumbnail>
</item>

<item>
<title>Zero Dark Thirty (2012) 720p</title>
<link>http://vidto.me/4fo8eme0hoeh</link>
<thumbnail>http://www.aceshowbiz.com/images/still/zero-dark-thirty-2012-poster03.jpg</thumbnail>
</item>

<item>
<title>Mission: Impossible II (2000)</title>
<link>http://vidto.me/5yxxbkfq0qrg</link>
<thumbnail>http://ia.media-imdb.com/images/M/MV5BODI4Mzk0NDU0NF5BMl5BanBnXkFtZTcwNTczODQwNA@@._V1_SX640_SY720_.jpg</thumbnail>
</item>

<item>
<title>RED (2010)</title>
<link>http://vidto.me/pbffy2nuhwsk</link>
<thumbnail>http://www.beyondhollywood.com/uploads/2010/03/new-red-poster-all-cast.jpg</thumbnail>
</item>

<item>
<title>Salt (2010) 720p</title>
<link>http://180upload.com/vdycmntflsmc</link>
<thumbnail>http://www.impawards.com/2010/posters/salt.jpg</thumbnail>
</item>

<item>
<title>Law Abiding Citizen (2009) 720p</title>
<link>http://movreel.com/42ihxt5niddc#</link>
<thumbnail>http://www.filmofilia.com/wp-content/uploads/2009/09/law_abiding_citizen_poster.jpg</thumbnail>
</item>

<item>
<title>Safe House (2012)</title>
<link>http://movreel.com/9ppcfdztjd6b</link>
<thumbnail>http://www.filmtrophy.com/wp-content/uploads/2012/01/Safe-House_Poster-2.jpg</thumbnail>
</item>

<item>
<title>Patriot Games (1992)</title>
<link>http://movreel.com/m1m2j10krp5i</link>
<thumbnail>http://www.impawards.com/1992/posters/patriot_games.jpg</thumbnail>
</item>

<item>
<title>Mr. & Mrs. Smith (2005) 720p</title>
<link>http://movreel.com/rmx8cnxxfwxd</link>
<thumbnail>http://upload.wikimedia.org/wikipedia/en/b/b4/Mr_and_mrs_smith_poster.jpg</thumbnail>
</item>

<item>
<title>True Lies (1994) 720p</title>
<link>http://vodlocker.com/umukp29ea824</link>
<thumbnail>https://encrypted-tbn1.gstatic.com/images?q=tbn:ANd9GcTk9iT1kAZW4QX7IuDiLtvmrEdwya03tZ3kzSwyKQ_1wGPqKlUf</thumbnail>
</item>

<item>
<title>Spies Like Us (1985)</title>
<link>http://movreel.com/gqwweft7h1w3</link>
<thumbnail>http://cf2.imgobject.com/t/p/original/2rUMMrs3YnMIwgprtbjzfJlnvLG.jpg</thumbnail>
</item>

<item>
<title>Breach (2007) 720p</title>
<link>http://movreel.com/ujytu8ypgmok#</link>
<thumbnail>https://encrypted-tbn1.gstatic.com/images?q=tbn:ANd9GcSmDaMPuAV2-yOaHyLDnLbcZBZ6W7LALij5luCGwW25ZXKHYu5y6w</thumbnail>
</item>

<item>
<title>The Bourne Legacy (2012)</title>
<link>http://played.to/4wijttiy181k</link>
<thumbnail>http://img4.wikia.nocookie.net/__cb20131211055711/scratchpad/images/3/3e/2012_-_The_Bourne_Legacy_Movie_Poster_-2.jpg</thumbnail>
</item>

<item>
<title>Munich (2005)</title>
<link>http://movreel.com/wah225iiaybm#</link>
<thumbnail>https://encrypted-tbn2.gstatic.com/images?q=tbn:ANd9GcQAoEjfbdXbKpB1bmWW5E4PWIwo02s-CakUB3iLvbH6VHNs43MASg</thumbnail>
</item>

<item>
<title>Burn After Reading (2008)</title>
<link>http://played.to/aitjerw91cen</link>
<thumbnail>https://encrypted-tbn0.gstatic.com/images?q=tbn:ANd9GcRTQnhZPk6TM21HbXQ_P6NewZkqYCLIW3cMdkoE5GkGRi1z8Mer</thumbnail>
</item>

<item>
<title>Once Upon a Time in Mexico (2003) 720p</title>
<link>http://vodlocker.com/3afpzc4lgkkc</link>
<thumbnail>http://images.moviepostershop.com/once-upon-a-time-in-mexico-movie-poster-2003-1020214292.jpg</thumbnail>
</item>

<item>
<title>RED 2 (2013)</title>
<link>http://vidto.me/s0we9zdj3v40</link>
<thumbnail>http://www.impawards.com/2013/posters/red_two_ver12.jpg</thumbnail>
</item>

<item>
<title>The A-Team (2010) 720p</title>
<link>http://movreel.com/4z97bwrf427u</link>
<thumbnail>https://encrypted-tbn0.gstatic.com/images?q=tbn:ANd9GcRH8_ITXlrlhUJFnElvmSnyLszFIGDRMd45Q9sXfMqmgNO6StD3fQ</thumbnail>
</item>

<item>
<title>This Means War (2012) 720p</title>
<link>http://movreel.com/lt9g08rhvj0z</link>
<thumbnail>http://www.beyondhollywood.com/uploads/2011/09/This-Means-War-2012-Movie-Poster.jpg</thumbnail>
</item>

<item>
<title>Confessions of a Dangerous Mind (2002)</title>
<link>http://played.to/mc2cb8p9kdpv</link>
<thumbnail>http://api.ning.com/files/uz-lXKZqhgs*-ERdMN1awQN7y3VXZBYdnzgrum--dEpEMTGwn7RBQAVCKuMSin339PzoX9ui89lMYoxrBfS60UPis3Jk2fnY/confessions_of_a_dangerous_mind_01.jpg</thumbnail>
</item>

<item>
<title>The Men Who Stare at Goats (2009) 720p</title>
<link>http://movreel.com/do4c71ytrqed</link>
<thumbnail>http://www.impawards.com/2009/posters/men_who_stare_at_goats.jpg</thumbnail>
</item>

<item>
<title>The Quiet American (2002)</title>
<link>http://vodlocker.com/dgdofggaox9l</link>
<thumbnail>http://ia.media-imdb.com/images/M/MV5BMjE2NTUxNTE3Nl5BMl5BanBnXkFtZTYwNTczMTg5._V1_SX214_AL_.jpg</thumbnail>
</item>

<item>
<title>Tinker Tailor Soldier Spy (2011) 720p</title>
<link>http://movreel.com/9nhodbk9zpo9</link>
<thumbnail>https://encrypted-tbn3.gstatic.com/images?q=tbn:ANd9GcQPGNMwPSUBvCnBf_UbWXzAHvPGbHwK2J_MPUvlsDvIyYbTGjtW</thumbnail>
</item>

<item>
<title>Fair Game (2010)</title>
<link>http://movreel.com/okzfq69gwcy1#</link>
<thumbnail>https://encrypted-tbn3.gstatic.com/images?q=tbn:ANd9GcQ9_Ygf1jGqN4vVOnPGMVB3cLyIQpvCw5VVA7xe-Lqy9ZUrU9lm6g</thumbnail>
</item>

<item>
<title>Jack Ryan: Shadow Recruit (2014) 720p</title>
<link>http://movreel.com/654i5ll5bjoo.html</link>
<thumbnail>http://cdn-static.denofgeek.com/sites/denofgeek/files/styles/insert_main_wide_image/public/jack_ryan.jpg?itok=1tGTjCJI</thumbnail>
</item>

<item>
<title>Nothing But the Truth (2008)</title>
<link>http://stagevu.com/video/iuhrkxhwjuub</link>
<thumbnail>https://encrypted-tbn0.gstatic.com/images?q=tbn:ANd9GcTqSJPVplK9gE7amG5wyF2Gw--VBjY5j_1GIDN52j_gZBi6QZ4N4Q</thumbnail>
</item>

<item>
<title>The Expendables (2010) 720p</title>
<link>http://vodlocker.com/4t63gpjf6fvp</link>
<thumbnail>http://www.impawards.com/2010/posters/expendables_ver9.jpg</thumbnail>
</item>

<item>
<title>Agent Cody Banks (2003)</title>
<link>http://vodlocker.com/zpnzgarqdjxb</link>
<thumbnail>http://www.impawards.com/2003/posters/agent_cody_banks_xlg.jpg</thumbnail>
</item>

<item>
<title>The Long Kiss Goodnight (1996)</title>
<link>http://stagevu.com/video/swnrnvfdiwoh</link>
<thumbnail>http://images.moviepostershop.com/the-long-kiss-goodnight-movie-poster-1996-1020190502.jpg</thumbnail>
</item>

<item>
<title>Colombiana (2011) 720p</title>
<link>http://movreel.com/f5p3ach1a221</link>
<thumbnail>https://encrypted-tbn1.gstatic.com/images?q=tbn:ANd9GcRipwYktxDGmQIEAGmXzsXNsCA1c2tE9-iOYrdoE1c2IVsUUAc1</thumbnail>
</item>
























