#######################################################################################################################################
<poster>MafiaTVRepo</poster>
<fanart></fanart>
#######################################################################################################################################

##############################################################################################################################


<item>
<title>Yellowstone</title>
<link>http://www.nowvideo.sx/video/tejplgfhsrplc</link>
<thumbnail>http://ecx.images-amazon.com/images/I/51f7inv1s5L.jpg</thumbnail>
</item>

<item>
<title>Ghost ships of the Great Lakes</title>
<link>http://www.firedrive.com/file/EA8D11BF465AF524</link>
<thumbnail>http://www.zoetv.net/blog/wp-content/uploads/2011/05/ghostships1.jpeg</thumbnail>
</item>

<item>
<title>The Human Family Tree</title>
<link>http://www.firedrive.com/file/TAF3VDG7I2SG0KS4</link>
<thumbnail>http://www.beutifulmagazine.com/wp-content/uploads/2013/02/Human-Family-Tree.jpg</thumbnail>
</item>

<item>
<title>national geographic the night stalker</title>
<link>http://www.firedrive.com/file/E9BB45BC1255D451</link>
<thumbnail>http://i1.ytimg.com/vi/n6WUVDasCtg/0.jpg</thumbnail>
</item>

<item>
<title>The King’s Speech: Revealed</title>
<link>http://www.videoweed.es/file/581006ab7440b</link>
<thumbnail>https://encrypted-tbn2.gstatic.com/images?q=tbn:ANd9GcTTwHAhQ2WdxaP26Py8KXfGzAmqtL1_ZhZniLw72BrMVb4VKA7swQ</thumbnail>
</item>

<item>
<title>Daytona Biker Rally</title>
<link>http://www.nowvideo.sx/video/hhzyxvzcdqagd</link>
<thumbnail>http://www.filmai.in/uploads/posts/2011-05/1306837966_58d62_.jpg</thumbnail>
</item>

<item>
<title>Warren Buffett The Modern Midas</title>
<link>http://www.sockshare.com/file/54540DA109F27FE9#</link>
<thumbnail>http://3.bp.blogspot.com/-1BFzqQogxZI/TaX9yn5Bx1I/AAAAAAAAJ4I/tLNPW-RaIB4/s800/Warren-Buffett-Rolex-President.jpg</thumbnail>
</item>

<item>
<title>Ancient Astronauts</title>
<link>http://www.sockshare.com/file/511862DC39EDED12#</link>
<thumbnail>http://www.the-savoisien.com/blog/public/img5/ancient_astronauts.png</thumbnail>
</item>

<item>
<title>Killing Lincoln</title>
<link>http://www.firedrive.com/file/96639DAD9A6C62D9</link>
<thumbnail>http://seslercompany.files.wordpress.com/2013/02/killing_lincoln_jb_blast.jpg</thumbnail>
</item>

<item>
<title>Mystery Files Nostradamus</title>
<link>http://www.sockshare.com/file/0CC9400B93AD6BA6#</link>
<thumbnail>http://fontwarez.ru/uploads/posts/2011-05/1306499314_c500.jpg</thumbnail>
</item>

<item>
<title>King Of Coke Living The High Life</title>
<link>http://www.nowvideo.sx/video/b2f360d8b2d7f</link>
<thumbnail>http://i48.fastpic.ru/big/2013/0521/bd/8cefd7b8e2d20e9e8020a13090982fbd.jpg</thumbnail>
</item>

<item>
<title>Kon Tiki The Incredible True Story</title>
<link>http://www.sockshare.com/file/3302890009951EF3#</link>
<thumbnail>http://www.showbizjunkies.com/wp-content/uploads/2013/04/kon-tiki-poster.jpg</thumbnail>
</item>

<item>
<title>The Wild West True Grit Convert</title>
<link>http://www.nowvideo.sx/video/00f2a9e0e21fd</link>
<thumbnail>http://i.jeded.com/i/national-geographic-wild-the-wild-west.20853.jpg</thumbnail>
</item>

<item>
<title>Ultimate Tutankhamun</title>
<link>http://www.firedrive.com/file/A570DBDD93E78D82</link>
<thumbnail>http://i43.tower.com/images/mm100076284/tutankhamun-golden-age-pharaohs-official-companion-book-exhibition-kenneth-garrett-hardcover-cover-art.jpg</thumbnail>
</item>

<item>
<title>Sex How It Works</title>
<link>http://www.sockshare.com/file/406FC7E61CF779B0#</link>
<thumbnail>https://encrypted-tbn2.gstatic.com/images?q=tbn:ANd9GcSDwWXj1wTTJQY0AMUcrV2haM2AutlvVqFDs2O3qQCkUrAymqiL</thumbnail>
</item>

<item>
<title>Finding The Lost Da Vinci</title>
<link>http://www.nowvideo.ch/video/849c6b309dd0b</link>
<thumbnail>http://s017.radikal.ru/i431/1206/23/996388dade5f.jpg</thumbnail>
</item>

<item>
<title>Wingsuit Daredevil</title>
<link>http://www.firedrive.com/file/4DF45CB1BD8EC904</link>
<thumbnail>http://theglobalherald.com/wp-content/uploads/2013/11/jeb-corliss-wingsuit-flying-660x330.jpg</thumbnail>
</item>

<item>
<title>Killing Kennedy</title>
<link>http://played.to/ieodcxhd96io/National.Geographic.Killing.Kennedy.HDTV.XviD-AFG_wso.avi</link>
<thumbnail>http://assets-s3.usmagazine.com/uploads/assets/articles/67298-killing-kennedy-poster-art-revealed-featuring-rob-lowe-as-john-f-kennedy/1382040607_killing-kennedy-article.jpg</thumbnail>
</item>

<item>
<title>Snakes On A Plane</title>
<link>http://www.nowvideo.sx/video/532e2cf939a1e</link>
<thumbnail>https://encrypted-tbn1.gstatic.com/images?q=tbn:ANd9GcRsyaPM2PXpyPGSHiXbGTwBCTtQ_VgYCK9N-XCTcrLRohAx7apo</thumbnail>
</item>

<item>
<title>Virgin Galactic Space Trip Convert</title>
<link>http://www.nowvideo.sx/video/eeo57nmsj3cie</link>
<thumbnail>http://www.qgits.org/wp-content/uploads/2013/07/Top-5-Crazy-Gifts-Katy-P.jpg</thumbnail>
</item>

<item>
<title>Woman raised by monkeys</title>
<link>http://played.to/gok6r1g7yx88/national.geographic.woman.raised.by.monkeys.hdtv.x264-knifesharp_wso.mp4</link>
<thumbnail>http://img.rlsbb.com/images/2013/12/13/Woman_Raised_By_Monkeys.jpg</thumbnail>
</item>

<item>
<title>The Lost Diary Of Dr Livingstone</title>
<link>http://www.nowvideo.sx/video/107dbe10da9be</link>
<thumbnail>http://i60.fastpic.ru/big/2013/1218/db/10879e0ed20374fbe5e72de0ccfb37db.jpg</thumbnail>
</item>

<item>
<title>Ison Comet Of The Century Repack</title>
<link>http://www.nowvideo.sx/video/cc90d93e7db9f</link>
<thumbnail>http://i742.photobucket.com/albums/xx68/aylpic/18/18001/NGCIsonComet.jpg</thumbnail>
</item>

<item>
<title>Jack of all trades</title>
<link>http://played.to/n2zr3ngos9mv/national.geographic.jack.of.all.trades.2013.hdtv.x264-w4f_wso.mp4</link>
<thumbnail>http://i.imgur.com/7ac3vka.jpg</thumbnail>
</item>

<item>
<title>Miracle landing on the hudson</title>
<link>http://played.to/niqzvdbjb3za/national.geographic.miracle.landing.on.the.hudson.hdtv.x264-knifesharp_wso.mp4</link>
<thumbnail>http://img.rlsbb.com/images/2014/01/06/hudson-jpg.jpg</thumbnail>
</item>

<item>
<title>Man vs YouTube</title>
<link>http://played.to/mz4gh2sr7uic/National.Geographic.Man.vs.YouTube.DSR.x264-W4F_wso.mp4</link>
<thumbnail>http://i33.fastpic.ru/big/2014/0214/23/c1c58b57f75bfedf9a7f02cbea53ac23.jpg</thumbnail>
</item>

<item>
<title>The skyjacker that got away</title>
<link>http://played.to/zc0zfubas8a9/national.geographic.the.skyjacker.that.got.away.dsr.x264-w4f_wso.mp4</link>
<thumbnail>http://edgewest.com/wp-content/gallery/skyjacker/the-skyjacker-that-got-away-1.jpg</thumbnail>
</item>

<item>
<title>Time Scanners Jerusalem</title>
<link>http://played.to/1v8dwebvq5qx/National.Geographic.Time.Scanners.Jerusalem.HDTV.x264-MoTv_wso.mp4</link>
<thumbnail>http://upload.wikimedia.org/wikipedia/en/b/b5/Final_poster_of_the_2013_documentary_film_entitled_Jerusalem.jpg</thumbnail>
</item>

<item>
<title>Ten Years On Mars</title>
<link>http://www.nowvideo.sx/video/84909526633bb</link>
<thumbnail>http://ia.media-imdb.com/images/M/MV5BMjAwMDcwNjg3OF5BMl5BanBnXkFtZTcwMDQ1MjQxMw@@._V1_SY317_CR5,0,214,317_.jpg</thumbnail>
</item>

<item>
<title>Mennonite Made</title>
<link>http://played.to/mhfhnglkx13i/National.Geographic.Mennonite.Made.HDTV.XviD-AFG_wso.avi</link>
<thumbnail>http://img.rlsbb.com/images/2014/02/19/menn.jpg</thumbnail>
</item>

<item>
<title>Live from Space</title>
<link>http://played.to/yvzadysyadvf/National.Geographic.Live.from.Space.2014.HDTV.XviD-AFG_wso.avi</link>
<thumbnail>http://nathanieljames.com/assets/natgeo_live_from_space_6.jpg</thumbnail>
</item>

<item>
<title>The Real Pompeii</title>
<link>http://played.to/2uvqolmcg85k/National.Geographic.The.Real.Pompeii.HDTV.x264-W4F_wso.mp4</link>
<thumbnail>http://1.bp.blogspot.com/-OndKi1WjNJY/UwhNb_kZGuI/AAAAAAAAQ1A/muvLqCA-XJA/s1600/National.Geographic.The.Real.Pompeii.jpg</thumbnail>
</item>

<item>
<title>Inside the Hunt for the Boston Bombers</title>
<link>http://played.to/vow7ngfuek79</link>
<thumbnail>http://pixhost.me/avaxhome/f8/2f/002c2ff8_medium.jpeg</thumbnail>
</item>

<item>
<title>The Jesus Mysteries</title>
<link>http://played.to/x0mw40qrrxqe</link>
<thumbnail>http://s6.postimg.org/hyhokddbl/The_Jesus_Mysteries.png</thumbnail>
</item>

<item>
<title>Taboo Addiction (2011)</title>
<link>http://www.sockshare.com/file/8EE4AB34E9C99557#</link>
<thumbnail>http://2.bp.blogspot.com/-xZrBIuV4eR4/Tw1IjJ9l9rI/AAAAAAAAA4A/8jWDL7wl20Y/s1600/National-Geographic-Taboo-Addiction-HDTV-XviD-DiVERGE.jpg</thumbnail>
</item>

<item>
<title>Taboo Fat (2010)</title>
<link>http://www.sockshare.com/file/6AD70055F24B4212#</link>
<thumbnail>http://alphavilleherald.com/images/2011/05/real-life-roleplay.jpg</thumbnail>
</item>

<item>
<title>Taboo Fantasy Lives (2011)</title>
<link>http://www.sockshare.com/file/416892B33FFEBCEE#</link>
<thumbnail>http://i.imgur.com/aG9NY.jpg</thumbnail>
</item>

<item>
<title>Taboo Prison Love (2011)</title>
<link>http://www.sockshare.com/file/70BF49165F878F23#</link>
<thumbnail>http://www.episode-alert.com/images/poster/large/71985-1.jpg</thumbnail>
</item>

<item>
<title>Taboo Forbidden Love (2011)</title>
<link>http://www.firedrive.com/file/54A59B0141759AAA</link>
<thumbnail>http://www.episode-alert.com/images/poster/large/71985-1.jpg</thumbnail>
</item>

<item>
<title>Taboo Prostitution (2010)</title>
<link>http://www.sockshare.com/file/D9DE769D3164CFD7#</link>
<thumbnail>http://img215.imageshack.us/img215/5207/tabooprosution.jpg</thumbnail>
</item>

<item>
<title>Sex for Sale American Escort (2012)</title>
<link>http://www.firedrive.com/file/4FB1C067700C66D4</link>
<thumbnail>http://i48.fastpic.ru/big/2012/1128/08/72e8b2eaa6413b68c734ac08ba3d0908.jpg</thumbnail>
</item>

<item>
<title>Grand Canyon: National Parks Collection (2009)</title>
<link>http://www.firedrive.com/file/7492E6890F5385DE</link>
<thumbnail>http://ecx.images-amazon.com/images/I/516WZeWLRBL.jpg</thumbnail>
</item>

<item>Extreme Alaska Denali National Park (2008)</title>
<link>http://www.sockshare.com/file/07FD18C532E0F841#</link>
<thumbnail>http://media-cache-cd0.pinimg.com/736x/c0/07/13/c007135f97a0ac539c1843383dcf61d6.jpg</thumbnail>
</item>

<item>
<title>Kissinger (2011)</title>
<link>http://www.sockshare.com/file/FC52C9F77208118C#</link>
<thumbnail>http://1.bp.blogspot.com/-JZDSa-JHMnA/TnHoNHThnRI/AAAAAAAAMKE/sVQ0XE2GBZ8/s1600/Kissinger%2B%25282011%2529.jpg</thumbnail>
</item>

<item>
<title>Ipredator (2011)</title>
<link>http://www.firedrive.com/file/66D555CE8CF8AD3C</link>
<thumbnail>http://www.dvdandgifts.co.za/images/National%20Geo%20-%20Last%20feast%20of%20the%20crocodiles.jpg</thumbnail>
</item>

<item>
<title>Everglades (2009)</title>
<link>http://www.sockshare.com/file/D6EE66CD910C0D61#</link>
<thumbnail>http://www4.alibris-static.com/cover/u75331ssmll.jpg</thumbnail>
</item>

<item>
<title>Yellowstone (2011)</title>
<link>http://www.nowvideo.sx/video/tejplgfhsrplc</link>
<thumbnail>http://i.imgur.com/PUw58.jpg</thumbnail>
</item>

<item>
<title>DogTown (2009)</title>
<link>http://www.sockshare.com/file/66C2BF8D9C606D88#</link>
<thumbnail>http://www.dvd-bluray-reviews.com/big_images/dvd/National-Geographic-Dogtown---Friends-in-Need.jpg</thumbnail>
</item>

<item>
<title>Solitary Confinement (2010)</title>
<link>http://www.sockshare.com/file/69786608E2442365#</link>
<thumbnail>http://static1.vidics.ch/150/2/National_Geographic_Solitary_Confinement-39815.PNG</thumbnail>
</item>

<item>
<title>Brothers In War (2014)</title>
<link>http://vidbull.com/34br5utjsx2k.html</link>
<thumbnail>http://i.imgur.com/FJRS99D.jpg</thumbnail>
</item>

<item>
<title>National Geographic at 125 (2013)</title>
<link>http://www.nowvideo.sx/video/532454adb29e2</link>
<thumbnail>http://press.nationalgeographic.com/files/2013/01/usa_today_ng_125_cover-2-393x400.jpg</thumbnail>
</item>

<item>
<title>The Lion Whisper (2014)</title>
<link>http://played.to/6vgohxi068nv</link>
<thumbnail>http://media-cache-cd0.pinimg.com/236x/e8/61/f1/e861f14cbfd07009a6280f5d02e723ea.jpg</thumbnail>
</item>

<item>
<title>Wild Phantom Cat (2014)</title>
<link>http://played.to/azyyr6aev7zf</link>
<thumbnail>http://channel.nationalgeographic.com/exposure/content/photo/photo/663010_cat-nap_7hqdjmj4am3d2cszxsyeykq4xpncurxrbvj6lwuht2ya6mzmafma_610x457.jpg</thumbnail>
</item>

<item>
<title>Flying Squad The Real Sweeney (2014)</title>
<link>http://www.sockshare.com/file/52EE0134F9BC538A#</link>
<thumbnail>http://img.rlsbb.com/images/2014/02/05/7cec6356be14e42ffbbb21f7a7bc5f4e.jpg</thumbnail>
</item>

<item>
<title>Miracle Landing on the Hudson (2014)</title>
<link>http://www.nowvideo.sx/video/e1b6b17c99075</link>
<thumbnail>https://encrypted-tbn0.gstatic.com/images?q=tbn:ANd9GcRkzL6NjcxXqkMwy2rXKEbQmp7DixHi5-wFqNzFZKzM0NKZsQW_</thumbnail>
</item>

<item>
<title>Secret Service Files: Protecting the President (2013)</title>
<link>http://www.divxstage.eu/video/528a0277d733f</link>
<thumbnail>http://dokonline.com/uploads/posts/2013-02/1360088929_1.jpg</thumbnail>
</item>

<item>
<title>Nazi Underworld The Hess Enigma (2013)</title>
<link>http://www.nowvideo.sx/video/4a800e72d786f</link>
<thumbnail>http://yuq.me/tv/16/683/34067.jpg</thumbnail>
</item>

<item>
<title>American Blackout (2013) </title>
<link>http://www.divxstage.eu/video/526ed86e4918f</link>
<thumbnail>http://channel.nationalgeographic.com/exposure/content/photo/photo/2074272_american-blackout_yhhbui2h6fubfdyfdbahdhdawlncurxrbvj6lwuht2ya6mzmafma_740x416.jpg</thumbnail>
</item>

<item>
<title>Nazi Underworld Patient Hitler (2013)</title>
<link>http://www.nowvideo.sx/video/3wwpa9amr6uqf</link>
<thumbnail>http://rapidmoviez.com/data/images/movies/2013-07/nazi-underworld.jpg</thumbnail>
</item>

<item>
<title>9 11 Firehouse Ground Zero (2013)</title>
<link>http://www.nowvideo.sx/video/8tbvmv44o06ez</link>
<thumbnail>http://pixhost.me/avaxhome/78/59/00285978_medium.jpeg</thumbnail>
</item>

<item>
<title>World's Deadliest Lady Killers (2013)</title>
<link>http://www.nowvideo.sx/video/5a15b425bab61</link>
<thumbnail>http://b.vimeocdn.com/ts/454/535/454535057_640.jpg</thumbnail>
</item>

<item>
<title>Breakout The Texas Seven (2013)</title>
<link>http://www.nowvideo.sx/video/98d92c242c8e7</link>
<thumbnail>http://2.bp.blogspot.com/-FxW-ViXRkeM/Um__HfjrtkI/AAAAAAAAFMk/g3eXxtGKvlk/s1600/2741472_National_Geographic_Breakout_The_Texas_Seven.jpg</thumbnail>
</item>

<item>
<title>Secrets Of The Tang Treasure Ship (2009)</title>
<link>http://veehd.com/video/2297182_National-Geographic-Secrets-Of-The-Tang-Treasure-Ship-2009</link>
<thumbnail>http://kinofresh.tv/uploads/posts5/29670832/poster.jpg</thumbnail>
</item>

<item>
<title>Earth Investigated Super Diamonds (2009)</title>
<link>http://veehd.com/video/2297181_National-Geographic-Earth-Investigated-Super-Diamonds</link>
<thumbnail>http://i.imgur.com/Lid0w.jpg</thumbnail>
</item>

<item>
<title>Prehistoric Predators Terror Raptor (2007)</title>
<link>http://veehd.com/video/2459098_National-Geographic-Prehistoric-Predators-Terror-Raptor</link>
<thumbnail>http://www.usabit.com/fotos/5169.jpg</thumbnail>
</item>

<item>
<title>Generals At War Battle Of The Bulge (2005)</title>
<link>http://veehd.com/video/2459115_National-Geographic-Generals-At-War-Battle-Of-The-Bulge</link>
<thumbnail>http://thumbs.watchdocumentary.com/original/84c0846f0-1.jpg</thumbnail>
</item>

<item>
<title>Prehistoric Predators Killer Pig(2007)</title>
<link>http://veehd.com/video/2459109_National-Geographic-Prehistoric-Predators-Killer-Pig</link>
<thumbnail>http://img.hindilinks4u.net/2011/05/National-Geographic-Prehistoric-Predators-E04-Killer-Pig-Documentary-213x300.jpg</thumbnail>
</item>

<item>
<title>Prehistoric Predators Razor Jaws (2007)</title>
<link>http://veehd.com/video/2459111_National-Geographic-Prehistoric-Predators-Razor-Jaws</link>
<thumbnail>http://img.hindilinks4u.net/2011/05/National-Geographic-Prehistoric-Predators-E04-Killer-Pig-Documentary-213x300.jpg</thumbnail>
</item>

<item>
<title>Generals At War The Battle Of Midway (2009)</title>
<link>http://veehd.com/video/2459120_National-Geographic-Generals-At-War-The-Battle-Of-Midway</link>
<thumbnail>http://pixhost.me/avaxhome/0f/33/0012330f_medium.jpeg</thumbnail>
</item>

<item>
<title>Generals At War El Alamein (2009)</title>
<link>http://veehd.com/video/2459117_National-Geographic-Generals-At-War-El-Alamein</link>
<thumbnail>http://i52.fastpic.ru/big/2013/0218/8b/31047975770448abb4ba3531c78ef88b.jpg</thumbnail>
</item>

<item>
<title>Generals At War The Battle Of Kursk (2009)</title>
<link>http://veehd.com/video/2459121_National-Geographic-Generals-At-War-The-Battle-Of-Kursk</link>
<thumbnail>http://pixhost.me/avaxhome/61/30/00153061_medium.jpeg</thumbnail>
</item>

<item>
<title>Prehistoric Predators Megalodon</title>
<link>http://veehd.com/video/2459163_National-Geographic-Prehistoric-Predators-Megalodon</link>
<thumbnail>http://www.uneed2know.eu/image/r_586x360/general-photos/articles/Carcharodon_megalodon_hunting_big.jpg</thumbnail>
</item>

<item>
<title>Death of the Universe (2012)</title>
<link>http://veehd.com/video/2546054_National-Geographic-Death-of-the-Universe</link>
<thumbnail>http://img546.imageshack.us/img546/1664/deathoftheuniverse.jpg</thumbnail>
</item>

<item>
<title>Marijuana Nation (2008)</title>
<link>http://veehd.com/video/2752535_National-Geographic-Marijuana-Nation</link>
<thumbnail>http://image.bayimg.com/gapoaaadd.jpg</thumbnail>
</item>

<item>
<title>Super Snake Anacondas And Pythons (2005)</title>
<link>http://veehd.com/video/2990134_National-Geographic-Super-Snake-Anacondas-And-Pythons-2005</link>
<thumbnail>http://pixhost.me/avaxhome/6f/bb/0017bb6f_medium.jpeg</thumbnail>
</item>

<item>
<title>Kung Fu Killers: 10 Most Deadliest Weapons (2007)</title>
<link>http://veehd.com/video/3016410_National-Geographic-Kung-Fu-Killers-10-Most-Deadliest-Weapons</link>
<thumbnail>http://thumbs2.ebaystatic.com/d/l225/m/mvAxxHYSiyihHCsnrZ-kAWw.jpg</thumbnail>
</item>

<item>
<title>The Final Prophecy (2012)</title>
<link>http://veehd.com/video/3154892_national-geographic-2012-the-final-prophecy</link>
<thumbnail>http://www.shiftoftheage.com/wp-content/uploads/2011/01/National-Geographic-2012-The-Final-Prophecy.jpg</thumbnail>
</item>

<item>
<title>Emperors of the Ice (2007)</title>
<link>http://veehd.com/video/3284489_National-Geographic-Emperors-of-the-Ice-2007</link>
<thumbnail>http://i.simplecd.me/PNITdy7E.jpg</thumbnail>
</item>

<item>
<title>Living With Big Cats (2009)</title>
<link>http://veehd.com/video/3284492_National-Geographic-Living-With-Big-Cats-2009</link>
<thumbnail>http://animals.nationalgeographic.com/u/TvyamNb-BivtNwpvn7Sct0VFDulyAfA9wBcU0gVHVnqC5ghvVlz2YV6x9OoW-8Ds5pJSkuq0uafTB5lCAA8/</thumbnail>
</item>

<item>
<title>The Secret Bible Knights Templar</title>
<link>http://veehd.com/video/3469199_National-Geographic-The-Secret-Bible-Knights-Templar</link>
<thumbnail>http://pixhost.me/avaxhome/17/d3/0016d317_medium.jpeg</thumbnail>
</item>

<item>
<title>The Truth Behind Crop Circles</title>
<link>http://veehd.com/video/3617780_National-Geographic-The-Truth-Behind-Crop-Circles</link>
<thumbnail>http://www.eflbooks.co.uk/bookimages/9781424022236.jpg</thumbnail>
</item>

<item>
<title>The Incredible Human Machine (2007)</title>
<link>http://veehd.com/video/4117701_National-Geographic-The-Incredible-Human-Machine-2007</link>
<thumbnail>http://oblivion.cf.letterboxd.com/resized/film-poster/5/8/7/6/3/58763-national-geographic-incredible-human-machine-0-230-0-341-crop.jpg</thumbnail>
</item>

<item>
<title>MIND ALTERING DRUGS (2005)</title>
<link>http://veehd.com/video/4429812_MIND-ALTERING-DRUGS-2005-NATIONAL-GEOGRAPHIC-7P-Documentary-Collection</link>
<thumbnail>http://mindhacksblog.files.wordpress.com/2010/11/highsociety.jpg?w=158&h=220</thumbnail>
</item>

<item>
<title>ZOMBIE ALLIGATORS (2009)</title>
<link>http://veehd.com/video/4429814_ZOMBIE-ALLIGATORS-2009-NATIONAL-GEOGRAPHIC-7P-Documentary-Collection</link>
<thumbnail>http://img.rp.vhd.me/4429814_l5.jpg</thumbnail>
</item>

<item>
<title>Day Under Fire - Vietnam War</title>
<link>http://veehd.com/video/4502229_Day-Under-Fire-Vietnam-War-National-Geographic</link>
<thumbnail>http://www.cruzine.com/wp-content/uploads/2010/10/025.jpg</thumbnail>
</item>

<item>
<title>Hubbles Final Frontier</title>
<link>http://veehd.com/video/4502105_National-Geographic-Hubbles-Final-Frontier</link>
<thumbnail>http://mansyr.com/uploads/posts/2013-03/1362338485_hubbles-final-frontier.jpg</thumbnail>
</item>

<item>
<title>Engineering Connections - Illustrious</title>
<link>http://veehd.com/video/4503970_National-Geographic-Engineering-Connections-Illustrious</link>
<thumbnail>http://img809.imageshack.us/img809/8977/00166d14j.jpg</thumbnail>
</item>

<item>
<title>Engineering Connections - Airbus</title>
<link>http://veehd.com/video/4503983_National-Geographic-Engineering-Connections-Airbus</link>
<thumbnail>http://channel.nationalgeographic.com/exposure/content/photo/photo/1715_3333_ec_airbus-2_04700300_pec6h7ytenr4mwgxehecgrp6ilncurxrbvj6lwuht2ya6mzmafma_610x389.jpg</thumbnail>
</item>

<item>
<title>Flying Sky Monsters</title>
<link>http://veehd.com/video/4525310_National-Geographic-Flying-Sky-Monsters-2010-DVDRip-avi</link>
<thumbnail>http://www.turkcealtyazi.org/images/poster/9505186.jpg</thumbnail>
</item>

<item>
<title>Is it Real? When Aliens Attack</title>
<link>https://www.youtube.com/watch?v=LR3Y1e1ZVMQ</link>
<thumbnail>http://img14.imageshack.us/img14/3661/grakoffrunationalgeogra.jpg</thumbnail>
</item>

<item>
<title>The Sharks (1982)</title>
<link>http://www.sockshare.com/file/54D5302393CF83CD#</link>
<thumbnail>http://content7.flixster.com/movie/10/95/88/10958897_det.jpg</thumbnail>
</item>


